odoo/addons/sale_credit_point/README.rst
odoo/addons/sale_credit_point/__init__.py
odoo/addons/sale_credit_point/__manifest__.py
odoo/addons/sale_credit_point/data/res_currency.xml
odoo/addons/sale_credit_point/i18n/es.po
odoo/addons/sale_credit_point/i18n/fr.po
odoo/addons/sale_credit_point/i18n/sale_credit_point.pot
odoo/addons/sale_credit_point/models/__init__.py
odoo/addons/sale_credit_point/models/partner.py
odoo/addons/sale_credit_point/models/point_history.py
odoo/addons/sale_credit_point/models/sale_order.py
odoo/addons/sale_credit_point/security/groups.xml
odoo/addons/sale_credit_point/security/ir.model.access.csv
odoo/addons/sale_credit_point/static/description/icon.png
odoo/addons/sale_credit_point/tests/__init__.py
odoo/addons/sale_credit_point/tests/test_credit.py
odoo/addons/sale_credit_point/tests/test_credit_history.py
odoo/addons/sale_credit_point/tests/test_sale_order.py
odoo/addons/sale_credit_point/tests/test_wizard.py
odoo/addons/sale_credit_point/views/partner.xml
odoo/addons/sale_credit_point/views/point_history.xml
odoo/addons/sale_credit_point/wizards/__init__.py
odoo/addons/sale_credit_point/wizards/manage_credit_point.py
odoo/addons/sale_credit_point/wizards/manage_credit_point.xml
odoo_addon_sale_credit_point-15.0.1.1.0.1.dist-info/METADATA
odoo_addon_sale_credit_point-15.0.1.1.0.1.dist-info/WHEEL
odoo_addon_sale_credit_point-15.0.1.1.0.1.dist-info/top_level.txt
odoo_addon_sale_credit_point-15.0.1.1.0.1.dist-info/RECORD
